subnet/__init__.py
subnet/subnet.py
subnet-0.0.2.dist-info/LICENSE
subnet-0.0.2.dist-info/METADATA
subnet-0.0.2.dist-info/WHEEL
subnet-0.0.2.dist-info/top_level.txt
subnet-0.0.2.dist-info/RECORD
