Metadata-Version: 2.1
Name: subnet
Version: 0.0.2
Summary: A package to subnet ip address for static or dynamic networking.
Home-page: https://github.com/usamaimdadsian/subnet-pkg
Author: Usama Imdad
Author-email: usamaimdadsian@gmail.com
License: UNKNOWN
Platform: UNKNOWN
Classifier: Programming Language :: Python :: 3
Classifier: License :: OSI Approved :: MIT License
Classifier: Operating System :: OS Independent
Requires-Python: >=3.6
